INSTALL.rst
LICENSE
MANIFEST.in
README.rst
VERSION
requirements.txt
setup.py
tasks.py
src/maputil/__init__.py
src/maputil/__main__.py
src/maputil/__meta__.py
src/maputil/api.py
src/maputil/invmap.py
src/maputil/mapping.py
src/maputil/tools.py
src/maputil/types_defaultdict.py
src/maputil/types_frozendict.py
src/maputil/types_iddict.py
src/maputil/types_multimap.py
src/maputil/util.py
src/maputil.egg-info/PKG-INFO
src/maputil.egg-info/SOURCES.txt
src/maputil.egg-info/dependency_links.txt
src/maputil.egg-info/not-zip-safe
src/maputil.egg-info/requires.txt
src/maputil.egg-info/top_level.txt
src/maputil/tests/__init__.py
src/maputil/tests/__main__.py
src/maputil/tests/conftest.py
src/maputil/tests/test_documentation.py
src/maputil/tests/test_invmap.py
src/maputil/tests/test_maputil.py